openimis_be_payment_cycle-1.3.1.dist-info/licenses/LICENSE.md
payment_cycle/__init__.py
payment_cycle/admin.py
payment_cycle/apps.py
payment_cycle/gql_mutations.py
payment_cycle/gql_queries.py
payment_cycle/models.py
payment_cycle/schema.py
payment_cycle/services.py
payment_cycle/urls.py
payment_cycle/validations.py
payment_cycle/views.py
payment_cycle/migrations/0001_initial.py
payment_cycle/migrations/0002_add_pc_rights_to_admin.py
payment_cycle/migrations/0003_alter_historicalpaymentcycle_date_created_and_more.py
payment_cycle/migrations/0004_add_start_and_end_date.py
payment_cycle/migrations/0005_remove_run_month.py
payment_cycle/migrations/0006_auto_20240315_0943.py
payment_cycle/migrations/0007_paymentcyclemutation.py
payment_cycle/migrations/__init__.py
payment_cycle/signals/__init__.py
payment_cycle/tests/__init__.py
payment_cycle/tests/data.py
payment_cycle/tests/paymentCycleServiceTests.py
openimis_be_payment_cycle-1.3.1.dist-info/METADATA
openimis_be_payment_cycle-1.3.1.dist-info/WHEEL
openimis_be_payment_cycle-1.3.1.dist-info/top_level.txt
openimis_be_payment_cycle-1.3.1.dist-info/RECORD
